bazaar_cli/__init__.py
bazaar_cli/bazaarwrapper.py
bazaar_cli/common.py
bazaar_cli/main.py
bazaar_cli/mw_dl.py
bazaar_cli/mw_list.py
bazaar_cli-0.1.0.dist-info/METADATA
bazaar_cli-0.1.0.dist-info/WHEEL
bazaar_cli-0.1.0.dist-info/entry_points.txt
bazaar_cli-0.1.0.dist-info/RECORD
