Metadata-Version: 2.1
Name: bazaar-cli
Version: 0.1.0
Summary: Command line tool to list and download Malware Bazaar samples
Home-page: https://github.com/matteyeux/bazaar-cli
License: MIT
Keywords: malwarebazaar
Author: matteyeux
Requires-Python: >=3.10,<4.0
Classifier: Development Status :: 4 - Beta
Classifier: Intended Audience :: Developers
Classifier: Intended Audience :: Education
Classifier: Intended Audience :: System Administrators
Classifier: License :: OSI Approved :: MIT License
Classifier: Programming Language :: Python :: 3
Classifier: Programming Language :: Python :: 3.10
Classifier: Programming Language :: Python :: 3.11
Classifier: Programming Language :: Python :: 3.10
Classifier: Topic :: Utilities
Requires-Dist: click (>=8.1.3,<9.0.0)
Requires-Dist: click-default-group (>=1.2.2,<2.0.0)
Requires-Dist: pyzipper (>=0.3.6,<0.4.0)
Requires-Dist: requests (>=2.28.2,<3.0.0)
Requires-Dist: tabulate (>=0.9.0,<0.10.0)
Project-URL: Repository, https://github.com/matteyeux/bazaar-cli
